MANIFEST.in
VERSION
setup.py
tensorshield.ext.subtensor.egg-info/PKG-INFO
tensorshield.ext.subtensor.egg-info/SOURCES.txt
tensorshield.ext.subtensor.egg-info/dependency_links.txt
tensorshield.ext.subtensor.egg-info/requires.txt
tensorshield.ext.subtensor.egg-info/top_level.txt
tensorshield/ext/subtensor/__init__.py
tensorshield/ext/subtensor/_asyncsubtensor.py
tensorshield/ext/subtensor/_basestorage.py
tensorshield/ext/subtensor/_metagraphobserver.py
tensorshield/ext/subtensor/_metagraphthread.py
tensorshield/ext/subtensor/_metagraphuplink.py
tensorshield/ext/subtensor/package.json
tensorshield/ext/subtensor/storage/sql/__init__.py
tensorshield/ext/subtensor/storage/sql/_base.py
tensorshield/ext/subtensor/storage/sql/_metagraphblock.py
tensorshield/ext/subtensor/storage/sql/_neuronregistration.py
tensorshield/ext/subtensor/storage/sql/_registeredneurons.py